README.md
setup.py
bal_tools/__init__.py
bal_tools/avito_api.py
bal_tools/common.py
bal_tools/sbr_api.py
bal_tools/tg_event_messeger.py
bal_tools.egg-info/PKG-INFO
bal_tools.egg-info/SOURCES.txt
bal_tools.egg-info/dependency_links.txt
bal_tools.egg-info/not-zip-safe
bal_tools.egg-info/top_level.txt
bal_tools/flask/__init__.py
bal_tools/flask/api.py
bal_tools/flask/sessions.py
bal_tools/flask/test_case/__init__.py
bal_tools/flask/test_case/nosql.py