Metadata-Version: 2.1
Name: bal-tools
Version: 1.2.8
Summary: Black Acorn Labs tools library
Home-page: https://github.com/blackacornlabs/bal_tools
Author: BlackAcornLabs
Author-email: git@blackacorn.io
License: UNKNOWN
Platform: UNKNOWN
Classifier: Development Status :: 3 - Alpha
Classifier: Programming Language :: Python :: 3.8
Classifier: Intended Audience :: Developers
Classifier: Topic :: Software Development
Classifier: License :: OSI Approved :: MIT License
Classifier: Operating System :: OS Independent
Requires-Python: >=3.8
